flake8_2020.py
flake8_2020-1.8.1.dist-info/LICENSE
flake8_2020-1.8.1.dist-info/METADATA
flake8_2020-1.8.1.dist-info/WHEEL
flake8_2020-1.8.1.dist-info/entry_points.txt
flake8_2020-1.8.1.dist-info/top_level.txt
flake8_2020-1.8.1.dist-info/RECORD
