Metadata-Version: 2.1
Name: flake8-2020
Version: 1.8.1
Summary: flake8 plugin which checks for misuse of `sys.version` or `sys.version_info`
Home-page: https://github.com/asottile/flake8-2020
Author: Anthony Sottile
Author-email: asottile@umich.edu
License: MIT
Classifier: License :: OSI Approved :: MIT License
Classifier: Programming Language :: Python :: 3
Classifier: Programming Language :: Python :: 3 :: Only
Classifier: Programming Language :: Python :: Implementation :: CPython
Requires-Python: >=3.8
License-File: LICENSE
